simple_ad/Simple_AD.py
simple_ad/__init__.py
simple_ad-0.0.5.dist-info/LICENSE
simple_ad-0.0.5.dist-info/METADATA
simple_ad-0.0.5.dist-info/WHEEL
simple_ad-0.0.5.dist-info/top_level.txt
simple_ad-0.0.5.dist-info/RECORD
