Metadata-Version: 2.1
Name: simple-ad
Version: 0.0.5
Summary: A simple Active Directory Python module to reduce boilerplate and increase productivity.
Home-page: https://github.com/elongstreet88/Python_Simple_AD
Author: Eric Longstreet
Author-email: elongstreet88@gmail.com
License: UNKNOWN
Platform: UNKNOWN
Classifier: Programming Language :: Python :: 3
Classifier: License :: OSI Approved :: MIT License
Classifier: Operating System :: OS Independent
Requires-Python: >=3.6
